medsim3d/__init__.py
medsim3d/__pycache__/__init__.cpython-39.pyc
medsim3d/datasets/__init__.py
medsim3d/datasets/ieee_ic_3dbp.py
medsim3d/datasets/model_net.py
medsim3d/datasets/__pycache__/__init__.cpython-39.pyc
medsim3d/datasets/__pycache__/ieee_ic_3dbp.cpython-39.pyc
medsim3d/datasets/__pycache__/model_net.cpython-39.pyc
medsim3d/deeplearning/__init__.py
medsim3d/deeplearning/__pycache__/__init__.cpython-39.pyc
medsim3d/deeplearning/gan3d/__init__.py
medsim3d/deeplearning/gan3d/gan3d_core.py
medsim3d/deeplearning/gan3d/gan3d_parameters.py
medsim3d/deeplearning/gan3d/model.py
medsim3d/deeplearning/gan3d/tester.py
medsim3d/deeplearning/gan3d/trainer.py
medsim3d/deeplearning/gan3d/utils.py
medsim3d/deeplearning/gan3d/__pycache__/__init__.cpython-39.pyc
medsim3d/deeplearning/gan3d/__pycache__/gan3d_core.cpython-39.pyc
medsim3d/deeplearning/gan3d/__pycache__/gan3d_parameters.cpython-39.pyc
medsim3d/deeplearning/gan3d/__pycache__/model.cpython-39.pyc
medsim3d/deeplearning/gan3d/__pycache__/tester.cpython-39.pyc
medsim3d/deeplearning/gan3d/__pycache__/trainer.cpython-39.pyc
medsim3d/deeplearning/gan3d/__pycache__/utils.cpython-39.pyc
medsim3d/gui/__init__.py
medsim3d/gui/gui_human_body_shape_viewer.py
medsim3d/gui/gui_human_body_shape_viewer3d.py
medsim3d/gui/gui_human_viewer.py
medsim3d/gui/gui_human_viewer3d.py
medsim3d/gui/gui_viewer.py
medsim3d/gui/gui_viewer3d.py
medsim3d/gui/__pycache__/__init__.cpython-39.pyc
medsim3d/gui/__pycache__/gui_human_body_shape_viewer3d.cpython-39.pyc
medsim3d/gui/__pycache__/gui_human_viewer.cpython-39.pyc
medsim3d/gui/__pycache__/gui_human_viewer3d.cpython-39.pyc
medsim3d/gui/__pycache__/gui_viewer3d.cpython-39.pyc
medsim3d/models/__init__.py
medsim3d/models/mat_converter.py
medsim3d/models/mat_creator.py
medsim3d/models/obj_parser.py
medsim3d/models/obj_reader.py
medsim3d/models/off_reader.py
medsim3d/models/off_writer.py
medsim3d/models/ply_parser.py
medsim3d/models/point_csv_reader.py
medsim3d/models/viewer3d.py
MedSim3D-0.0.1a3.dist-info/LICENSE
MedSim3D-0.0.1a3.dist-info/METADATA
MedSim3D-0.0.1a3.dist-info/WHEEL
MedSim3D-0.0.1a3.dist-info/top_level.txt
MedSim3D-0.0.1a3.dist-info/RECORD
