Metadata-Version: 2.1
Name: MedSim3D
Version: 0.0.1a3
Summary: Medical Simulation Framework in the 3D Environment
Home-page: https://github.com/dhchenx/MedSim3D
Author: Donghua Chen
Author-email: douglaschan@126.com
License: MIT
Project-URL: Bug Reports, https://github.com/dhchenx/MedSim3D/issues
Project-URL: Source, https://github.com/dhchenx/MedSim3D
Keywords: medical education,simulation,agent-based modeling,3D
Platform: UNKNOWN
Classifier: Development Status :: 5 - Production/Stable
Classifier: Intended Audience :: Healthcare Industry
Classifier: Topic :: Scientific/Engineering :: Medical Science Apps.
Classifier: License :: OSI Approved :: MIT License
Classifier: Programming Language :: Python :: 3
Classifier: Programming Language :: Python :: 3.6
Classifier: Programming Language :: Python :: 3.7
Classifier: Programming Language :: Python :: 3.8
Classifier: Programming Language :: Python :: 3.9
Classifier: Programming Language :: Python :: 3 :: Only
Requires-Python: >=3.6, <4
License-File: LICENSE
Requires-Dist: tqdm
Requires-Dist: requests
Requires-Dist: quick-csv
Requires-Dist: numpy
Requires-Dist: cv2
Requires-Dist: pillow
Requires-Dist: pandas
Requires-Dist: matplotlib
Requires-Dist: scipy
Requires-Dist: skimage
Requires-Dist: sklearn
Requires-Dist: shapely
Requires-Dist: pyntcloud
Provides-Extra: dev
Requires-Dist: check-manifest ; extra == 'dev'
Provides-Extra: test
Requires-Dist: coverage ; extra == 'test'
